<scene version="0.5.0">
  <integrator type="path">
    <integer name="maxDepth" value="17"/>
  </integrator>
  <sensor type="perspective">
    <float name="fov" value="63.9704853333"/>
    <transform name="toWorld">
      <matrix value="-0.988479974356 -0.00428442603858 0.151294480316 -1.69048743622 -1.50337072586e-08 0.999599546565 0.0283071332954 1.27157602332 -0.151354784634 0.0279810060202 -0.98808375414 5.88653384733 -0.0 0.0 0.0 1.0 "/>
    </transform>
    <sampler type="sobol"/>
    <film type="ldrfilm">
      <string name="fileFormat" value="png"/>
      <integer name="height" value="720"/>
      <integer name="width" value="1280"/>
      <string name="pixelFormat" value="rgb"/>
      <float name="gamma" value="2.2"/>
      <boolean name="banner" value="false"/>
      <rfilter type="tent"/>
    </film>
  </sensor>
  <bsdf id="Walls" type="twosided">
    <bsdf type="diffuse">
      <rgb name="reflectance" value="0.654071, 0.67408, 0.8"/>
    </bsdf>
  </bsdf>
  <bsdf id="Lectern" type="twosided">
    <bsdf type="diffuse">
      <texture name="reflectance" type="bitmap"/>
    </bsdf>
  </bsdf>
  <bsdf id="FlagRed" type="twosided">
    <bsdf type="diffuse">
      <rgb name="reflectance" value="0.8, 0.008214, 0.0"/>
    </bsdf>
  </bsdf>
  <bsdf id="FlagWhite" type="twosided">
    <bsdf type="diffuse">
      <rgb name="reflectance" value="1.0, 1.0, 1.0"/>
    </bsdf>
  </bsdf>
  <bsdf id="FlagBase" type="twosided">
    <bsdf type="diffuse">
      <rgb name="reflectance" value="0.779661, 0.653162, 0.349188"/>
    </bsdf>
  </bsdf>
  <bsdf id="ChalkHolder" type="twosided">
    <bsdf type="diffuse">
      <rgb name="reflectance" value="0.8, 0.644901, 0.412119"/>
    </bsdf>
  </bsdf>
  <bsdf id="ProjectorScreen" type="twosided">
    <bsdf type="diffuse">
      <rgb name="reflectance" value="1.0, 1.0, 1.0"/>
    </bsdf>
  </bsdf>
  <bsdf id="StickyNote1" type="twosided">
    <bsdf type="diffuse">
      <rgb name="reflectance" value="0.612066, 0.612066, 0.612066"/>
    </bsdf>
  </bsdf>
  <bsdf id="Whiteboard" type="twosided">
    <bsdf type="diffuse">
      <rgb name="reflectance" value="1.0, 1.0, 1.0"/>
    </bsdf>
  </bsdf>
  <bsdf id="StickyNote7" type="twosided">
    <bsdf type="diffuse">
      <rgb name="reflectance" value="0.612066, 0.612066, 0.612066"/>
    </bsdf>
  </bsdf>
  <bsdf id="StickyNote8" type="twosided">
    <bsdf type="diffuse">
      <rgb name="reflectance" value="0.612066, 0.612066, 0.612066"/>
    </bsdf>
  </bsdf>
  <bsdf id="Bin2" type="twosided">
    <bsdf type="diffuse">
      <rgb name="reflectance" value="0.8, 0.717509, 0.190456"/>
    </bsdf>
  </bsdf>
  <bsdf id="Boxes2" type="twosided">
    <bsdf type="diffuse">
      <rgb name="reflectance" value="0.8, 0.791642, 0.388399"/>
    </bsdf>
  </bsdf>
  <bsdf id="Boxes1" type="twosided">
    <bsdf type="diffuse">
      <rgb name="reflectance" value="0.64, 0.472188, 0.319233"/>
    </bsdf>
  </bsdf>
  <bsdf id="StickyNote4" type="twosided">
    <bsdf type="diffuse">
      <rgb name="reflectance" value="0.612066, 0.612066, 0.612066"/>
    </bsdf>
  </bsdf>
  <bsdf id="Whiteboard2" type="twosided">
    <bsdf type="diffuse">
      <rgb name="reflectance" value="0.79311, 0.79311, 0.79311"/>
    </bsdf>
  </bsdf>
  <bsdf id="BluePencil" type="twosided">
    <bsdf type="diffuse">
      <rgb name="reflectance" value="0.0, 0.030764, 0.8"/>
    </bsdf>
  </bsdf>
  <bsdf id="GreenPencil" type="twosided">
    <bsdf type="diffuse">
      <rgb name="reflectance" value="0.145676, 0.64, 0.0"/>
    </bsdf>
  </bsdf>
  <bsdf id="RedPencil" type="twosided">
    <bsdf type="diffuse">
      <rgb name="reflectance" value="0.626651, 0.0, 0.0"/>
    </bsdf>
  </bsdf>
  <bsdf id="Bookshelf" type="twosided">
    <bsdf type="diffuse">
      <rgb name="reflectance" value="0.491301, 0.305177, 0.8"/>
    </bsdf>
  </bsdf>
  <bsdf id="Hallway" type="twosided">
    <bsdf type="diffuse">
      <rgb name="reflectance" value="0.784314, 0.784314, 0.784314"/>
    </bsdf>
  </bsdf>
  <bsdf id="CeilingLight" type="twosided">
    <bsdf type="roughplastic">
      <string name="distribution" value="ggx"/>
      <boolean name="nonlinear" value="true"/>
      <float name="alpha" value="0.1"/>
    </bsdf>
  </bsdf>
  <bsdf id="Black" type="twosided">
    <bsdf type="diffuse">
      <rgb name="reflectance" value="0.00631, 0.00631, 0.00631"/>
    </bsdf>
  </bsdf>
  <bsdf id="BlackPlastic" type="twosided">
    <bsdf type="roughplastic">
      <string name="distribution" value="ggx"/>
      <boolean name="nonlinear" value="true"/>
      <float name="alpha" value="0.1"/>
    </bsdf>
  </bsdf>
  <bsdf id="Projector" type="twosided">
    <bsdf type="diffuse">
      <rgb name="reflectance" value="0.00631, 0.00631, 0.00631"/>
    </bsdf>
  </bsdf>
  <bsdf id="ScreenEnds" type="twosided">
    <bsdf type="diffuse">
      <rgb name="reflectance" value="0.028991, 0.028991, 0.028991"/>
    </bsdf>
  </bsdf>
  <bsdf id="FoamEraser" type="twosided">
    <bsdf type="diffuse">
      <rgb name="reflectance" value="0.684615, 0.684615, 0.684615"/>
    </bsdf>
  </bsdf>
  <bsdf id="Whiteboard3" type="twosided">
    <bsdf type="roughplastic">
      <string name="distribution" value="ggx"/>
      <boolean name="nonlinear" value="true"/>
      <float name="alpha" value="0.05"/>
    </bsdf>
  </bsdf>
  <bsdf id="ChairWood" type="twosided">
    <bsdf type="roughplastic">
      <string name="distribution" value="ggx"/>
      <boolean name="nonlinear" value="true"/>
      <float name="alpha" value="0.05"/>
      <texture name="reflectance" type="bitmap"/>
    </bsdf>
  </bsdf>
  <bsdf id="ChairFrame" type="twosided">
    <bsdf type="roughconductor">
      <string name="distribution" value="ggx"/>
      <float name="alpha" value="0.1"/>
      <rgb name="k" value="9.223869, 6.269523, 4.837001"/>
      <rgb name="eta" value="1.65746, 0.880369, 0.521229"/>
    </bsdf>
  </bsdf>
  <bsdf id="ChairStainless" type="twosided">
    <bsdf type="conductor">
      <string name="distribution" value="ggx"/>
      <rgb name="k" value="9.223869, 6.269523, 4.837001"/>
      <rgb name="eta" value="1.65746, 0.880369, 0.521229"/>
    </bsdf>
  </bsdf>
  <bsdf id="Floor" type="twosided">
    <bsdf type="diffuse">
      <rgb name="reflectance" value="0.659224, 0.592438, 0.517401"/>
    </bsdf>
  </bsdf>
  <bsdf id="WoodFrame" type="twosided">
    <bsdf type="diffuse">
      <texture name="reflectance" type="bitmap"/>
    </bsdf>
  </bsdf>
  <bsdf id="WhiteboardFrame" type="twosided">
    <bsdf type="diffuse">
      <rgb name="reflectance" value="0.056173, 0.056173, 0.056173"/>
    </bsdf>
  </bsdf>
  <bsdf id="StickyNote3" type="twosided">
    <bsdf type="diffuse">
      <rgb name="reflectance" value="0.612066, 0.612066, 0.612066"/>
    </bsdf>
  </bsdf>
  <bsdf id="StickyNote5" type="twosided">
    <bsdf type="diffuse">
      <rgb name="reflectance" value="0.612066, 0.612066, 0.612066"/>
    </bsdf>
  </bsdf>
  <bsdf id="StickyNote6" type="twosided">
    <bsdf type="diffuse">
      <rgb name="reflectance" value="0.612066, 0.612066, 0.612066"/>
    </bsdf>
  </bsdf>
  <bsdf id="Speakers" type="twosided">
    <bsdf type="diffuse">
      <rgb name="reflectance" value="0.03598, 0.03598, 0.03598"/>
    </bsdf>
  </bsdf>
  <bsdf id="Wall" type="twosided">
    <bsdf type="diffuse">
      <rgb name="reflectance" value="0.450837, 0.453663, 0.499605"/>
    </bsdf>
  </bsdf>
  <bsdf id="WindowFrame" type="twosided">
    <bsdf type="roughconductor">
      <string name="distribution" value="ggx"/>
      <float name="alpha" value="0.1"/>
      <rgb name="k" value="9.223869, 6.269523, 4.837001"/>
      <rgb name="eta" value="1.65746, 0.880369, 0.521229"/>
    </bsdf>
  </bsdf>
  <bsdf id="Bin1" type="twosided">
    <bsdf type="diffuse">
      <rgb name="reflectance" value="0.327125, 0.578596, 0.280561"/>
    </bsdf>
  </bsdf>
  <bsdf id="Rubber" type="twosided">
    <bsdf type="diffuse">
      <rgb name="reflectance" value="0.687031, 0.715465, 0.560499"/>
    </bsdf>
  </bsdf>
  <bsdf id="FluorescentTube" type="twosided">
    <bsdf type="plastic">
      <string name="distribution" value="ggx"/>
      <boolean name="nonlinear" value="true"/>
    </bsdf>
  </bsdf>
  <bsdf id="StickyNote2" type="twosided">
    <bsdf type="diffuse">
      <rgb name="reflectance" value="0.612066, 0.612066, 0.612066"/>
    </bsdf>
  </bsdf>
</scene>
